CODE_OF_CONDUCT.md
CONTRIBUTING.md
LICENSE
MANIFEST.in
README.md
requirements.txt
setup.cfg
setup.py
ScaffoldGraphNew.egg-info/PKG-INFO
ScaffoldGraphNew.egg-info/SOURCES.txt
ScaffoldGraphNew.egg-info/dependency_links.txt
ScaffoldGraphNew.egg-info/entry_points.txt
ScaffoldGraphNew.egg-info/requires.txt
ScaffoldGraphNew.egg-info/top_level.txt
analysis/__init__.py
analysis/diversity.py
analysis/enrichment.py
analysis/general.py
analysis/representation.py
core/__init__.py
core/fragment.py
core/graph.py
core/scaffold.py
io/__init__.py
io/dataframe.py
io/sdf.py
io/smiles.py
io/supplier.py
io/tsv.py
prioritization/__init__.py
prioritization/generic_rules.py
prioritization/original_rules.py
prioritization/prioritization_rules.py
prioritization/prioritization_ruleset.py
prioritization/rule_io.py
scaffoldgraphnew/__init__.py
scaffoldgraphnew/network.py
scaffoldgraphnew/tree.py
scaffoldgraphnew/analysis/__init__.py
scaffoldgraphnew/analysis/diversity.py
scaffoldgraphnew/analysis/enrichment.py
scaffoldgraphnew/analysis/general.py
scaffoldgraphnew/analysis/representation.py
scaffoldgraphnew/core/__init__.py
scaffoldgraphnew/core/fragment.py
scaffoldgraphnew/core/graph.py
scaffoldgraphnew/core/scaffold.py
scaffoldgraphnew/io/__init__.py
scaffoldgraphnew/io/dataframe.py
scaffoldgraphnew/io/sdf.py
scaffoldgraphnew/io/smiles.py
scaffoldgraphnew/io/supplier.py
scaffoldgraphnew/io/tsv.py
scaffoldgraphnew/prioritization/__init__.py
scaffoldgraphnew/prioritization/generic_rules.py
scaffoldgraphnew/prioritization/original_rules.py
scaffoldgraphnew/prioritization/prioritization_rules.py
scaffoldgraphnew/prioritization/prioritization_ruleset.py
scaffoldgraphnew/prioritization/rule_io.py
scaffoldgraphnew/scripts/__init__.py
scaffoldgraphnew/scripts/generate.py
scaffoldgraphnew/scripts/misc.py
scaffoldgraphnew/scripts/operations.py
scaffoldgraphnew/scripts/run.py
scaffoldgraphnew/utils/__init__.py
scaffoldgraphnew/utils/aggregate.py
scaffoldgraphnew/utils/bipartite.py
scaffoldgraphnew/utils/cache.py
scaffoldgraphnew/utils/logging.py
scaffoldgraphnew/utils/misc.py
scaffoldgraphnew/vis/__init__.py
scaffoldgraphnew/vis/base.py
scaffoldgraphnew/vis/utils.py
scaffoldgraphnew/vis/notebook/__init__.py
