Metadata-Version: 2.1
Name: ScaffoldGraphNew
Version: 1.1.5
Summary: ScaffoldGraph is an open-source cheminformatics library, built using RDKit and NetworkX for generating scaffold networks and scaffold trees.
Home-page: https://github.com/UCLCheminformatics/scaffoldgraph
Author: Oliver Scott
Author-email: oliver.scott.17@ucl.ac.uk
License: MIT
Download-URL: https://github.com/UCLCheminformatics/scaffoldgraph/archive/1.1.5.tar.gz
Keywords: rdkit,networkx,cheminformatics,scaffolds,scaffold tree,scaffold network
Platform: UNKNOWN
Classifier: License :: OSI Approved :: MIT License
Classifier: Programming Language :: Python :: 3
Classifier: Operating System :: OS Independent
Classifier: Topic :: Scientific/Engineering
Classifier: Topic :: Scientific/Engineering :: Bio-Informatics
Classifier: Topic :: Scientific/Engineering :: Chemistry
Requires-Python: >=3.6
Provides-Extra: vis
Provides-Extra: rdkit
License-File: LICENSE
